pyproject_autoflake/__init__.py
pyproject_autoflake/__main__.py
pyproject_autoflake/pautoflake.py
pyproject_autoflake-1.0.2.dist-info/entry_points.txt
pyproject_autoflake-1.0.2.dist-info/LICENSE
pyproject_autoflake-1.0.2.dist-info/WHEEL
pyproject_autoflake-1.0.2.dist-info/METADATA
pyproject_autoflake-1.0.2.dist-info/RECORD
