Metadata-Version: 2.1
Name: pyproject-autoflake
Version: 1.0.2
Summary: pyproject-autoflake (pautoflake), a monkey patching wrapper to connect autoflake with pyproject.toml configuration.
Home-page: https://github.com/quwac/pyproject-autoflake
Keywords: formatter,autoflake,pyproject.toml
Author: quwac
Author-email: 53551867+quwac@users.noreply.github.com
Requires-Python: >=3.6.2,<4.0.0
Classifier: Programming Language :: Python :: 3
Classifier: Programming Language :: Python :: 3.10
Classifier: Programming Language :: Python :: 3.7
Classifier: Programming Language :: Python :: 3.8
Classifier: Programming Language :: Python :: 3.9
Requires-Dist: autoflake
Requires-Dist: toml (>=0.10.1)
Project-URL: Repository, https://github.com/quwac/pyproject-autoflake
